task_commit/__init__.py
task_commit/core.py
task_commit/init.py
task_commit/locale/es/LC_MESSAGES/messages.mo
task_commit/locale/es/LC_MESSAGES/messages.po
task_commit/locale/pt_BR/LC_MESSAGES/messages.mo
task_commit/locale/pt_BR/LC_MESSAGES/messages.po
task_commit/main.py
task_commit/utils.py
task_commit-0.1.18.dist-info/LICENSE
task_commit-0.1.18.dist-info/METADATA
task_commit-0.1.18.dist-info/WHEEL
task_commit-0.1.18.dist-info/entry_points.txt
task_commit-0.1.18.dist-info/RECORD
