Metadata-Version: 2.3
Name: task-commit
Version: 0.1.18
Summary: Tool for formatting commits following the Conventional Commits pattern and recognizing Git Flow branches
License: MIT License
Author: Walefy Lima
Author-email: walefylima@gmail.com
Requires-Python: >=3.11
Classifier: License :: Other/Proprietary License
Classifier: Programming Language :: Python :: 3
Classifier: Programming Language :: Python :: 3.11
Classifier: Programming Language :: Python :: 3.12
Classifier: Programming Language :: Python :: 3.13
Classifier: Topic :: Software Development :: Build Tools
Classifier: Topic :: Software Development :: Libraries :: Python Modules
Requires-Dist: inquirer (>=3.4.0,<4.0.0)
Requires-Dist: prompt-toolkit (>=3.0.50,<4.0.0)
Project-URL: Bug Tracker, https://github.com/WalefyHG/Task_Commit/issues
Project-URL: Documentation, https://python-poetry.org/docs/
Project-URL: Homepage, https://python-poetry.org/
Project-URL: Repository, https://github.com/WalefyHG/Task_Commit
